CheckM2_modified-1.0.2.data/data/data/feature_ordering.json
CheckM2_modified-1.0.2.data/data/data/kegg_path_category_mapping.json
CheckM2_modified-1.0.2.data/data/data/min_ref_rsdata_v1.npz
CheckM2_modified-1.0.2.data/data/data/module_definitions.json
CheckM2_modified-1.0.2.data/data/models/cosine_table.pkl
CheckM2_modified-1.0.2.data/data/models/general_model_COMP.gbm
CheckM2_modified-1.0.2.data/data/models/model_CONT.gbm
CheckM2_modified-1.0.2.data/data/models/scaler.sav
CheckM2_modified-1.0.2.data/data/models/specific_model_COMP.hd5
CheckM2_modified-1.0.2.data/data/testrun/TEST1.tst
CheckM2_modified-1.0.2.data/data/testrun/TEST2.tst
CheckM2_modified-1.0.2.data/data/testrun/TEST3.tst
CheckM2_modified-1.0.2.data/data/version/diamond_path.json
CheckM2_modified-1.0.2.data/data/version/version_hashes_1.0.2.json
checkm2/__init__.py
checkm2/cli.py
checkm2/defaultValues.py
checkm2/diamond.py
checkm2/fileManager.py
checkm2/keggData.py
checkm2/metadata.py
checkm2/modelPostprocessing.py
checkm2/modelProcessing.py
checkm2/predictQuality.py
checkm2/prodigal.py
checkm2/sequenceClasses.py
checkm2/version.py
checkm2/versionControl.py
checkm2/zenodo_backpack.py
checkm2/data/feature_ordering.json
checkm2/data/kegg_path_category_mapping.json
checkm2/data/min_ref_rsdata_v1.npz
checkm2/data/module_definitions.json
checkm2/models/cosine_table.pkl
checkm2/models/general_model_COMP.gbm
checkm2/models/model_CONT.gbm
checkm2/models/scaler.sav
checkm2/models/specific_model_COMP.hd5
checkm2/testrun/TEST1.tst
checkm2/testrun/TEST2.tst
checkm2/testrun/TEST3.tst
checkm2/version/diamond_path.json
checkm2/version/version_hashes_1.0.2.json
CheckM2_modified-1.0.2.dist-info/LICENSE
CheckM2_modified-1.0.2.dist-info/METADATA
CheckM2_modified-1.0.2.dist-info/WHEEL
CheckM2_modified-1.0.2.dist-info/entry_points.txt
CheckM2_modified-1.0.2.dist-info/top_level.txt
CheckM2_modified-1.0.2.dist-info/RECORD
