Metadata-Version: 2.1
Name: CheckM2-modified
Version: 1.0.2
Summary: CheckM2 - Predicting the quality of metagenome-recovered bins
Home-page: https://github.com/chklovski/CheckM2
Author: Alex Chklovski
Author-email: chklovski@gmail.com
License: UNKNOWN
Platform: UNKNOWN
License-File: LICENSE
